chromadb/__init__.py
chromadb/app.py
chromadb/config.py
chromadb/errors.py
chromadb/types.py
chromadb/api/__init__.py
chromadb/api/fastapi.py
chromadb/api/local.py
chromadb/api/smartapi.py
chromadb/api/types.py
chromadb/api/models/Collection.py
chromadb/db/__init__.py
chromadb/db/base.py
chromadb/db/clickhouse.py
chromadb/db/duckdb.py
chromadb/db/migrations.py
chromadb/db/smartdb.py
chromadb/db/system.py
chromadb/db/impl/__init__.py
chromadb/db/impl/sqlite.py
chromadb/db/index/__init__.py
chromadb/db/index/hnswlib.py
chromadb/db/mixins/embeddings_queue.py
chromadb/db/mixins/sysdb.py
chromadb/ingest/__init__.py
chromadb/segment/__init__.py
chromadb/segment/impl/manager/local.py
chromadb/segment/impl/metadata/sqlite.py
chromadb/segment/impl/vector/local_hnsw.py
chromadb/server/__init__.py
chromadb/server/fastapi/__init__.py
chromadb/server/fastapi/types.py
chromadb/telemetry/__init__.py
chromadb/telemetry/events.py
chromadb/telemetry/posthog.py
chromadb/test/conftest.py
chromadb/test/test_api.py
chromadb/test/test_chroma.py
chromadb/test/test_config.py
chromadb/test/db/test_base.py
chromadb/test/db/test_migrations.py
chromadb/test/db/test_system.py
chromadb/test/db/migrations/00001-migration-1.psql.sql
chromadb/test/db/migrations/00001-migration-1.sqlite.sql
chromadb/test/db/migrations/00002-migration-2.psql.sql
chromadb/test/db/migrations/00002-migration-2.sqlite.sql
chromadb/test/db/migrations/00003-migration-3.psql.sql
chromadb/test/db/migrations/00003-migration-3.sqlite.sql
chromadb/test/hnswlib/test_hnswlib.py
chromadb/test/ingest/test_producer_consumer.py
chromadb/test/property/invariants.py
chromadb/test/property/strategies.py
chromadb/test/property/test_add.py
chromadb/test/property/test_collections.py
chromadb/test/property/test_cross_version_persist.py
chromadb/test/property/test_embeddings.py
chromadb/test/property/test_filtering.py
chromadb/test/property/test_persist.py
chromadb/test/segment/test_metadata.py
chromadb/test/segment/test_vector.py
smart_chromadb-0.1.dev734.dist-info/LICENSE
smart_chromadb-0.1.dev734.dist-info/METADATA
smart_chromadb-0.1.dev734.dist-info/WHEEL
smart_chromadb-0.1.dev734.dist-info/top_level.txt
smart_chromadb-0.1.dev734.dist-info/RECORD
