Metadata-Version: 2.1
Name: smart-chromadb
Version: 0.1.dev734
Summary: Chroma.
Author-email: Jeff Huber <jeff@trychroma.com>, Anton Troynikov <anton@trychroma.com>
Project-URL: Homepage, https://github.com/chroma-core/chroma
Project-URL: Bug Tracker, https://github.com/chroma-core/chroma/issues
Classifier: Programming Language :: Python :: 3
Classifier: License :: OSI Approved :: Apache Software License
Classifier: Operating System :: OS Independent
Requires-Python: >=3.7
License-File: LICENSE
Requires-Dist: pandas (>=1.3)
Requires-Dist: requests (>=2.28)
Requires-Dist: pydantic (>=1.9)
Requires-Dist: hnswlib (>=0.7)
Requires-Dist: clickhouse-connect (>=0.5.7)
Requires-Dist: duckdb (>=0.7.1)
Requires-Dist: fastapi (>=0.85.1)
Requires-Dist: uvicorn[standard] (>=0.18.3)
Requires-Dist: numpy (>=1.21.6)
Requires-Dist: posthog (>=2.4.0)
Requires-Dist: typing-extensions (>=4.5.0)
Requires-Dist: pulsar-client (>=3.1.0)
Requires-Dist: onnxruntime (>=1.14.1)
Requires-Dist: tokenizers (>=0.13.2)
Requires-Dist: tqdm (>=4.65.0)
Requires-Dist: overrides (>=7.3.1)
Requires-Dist: pymysql
Requires-Dist: graphlib-backport (>=1.0.3) ; python_version < "3.9"
